config/config.ini
config/defaults.ini
falcon_integration_gateway-3.4.0.dist-info/licenses/LICENSE
fig/__init__.py
fig/__main__.py
fig/falcon_data.py
fig/worker.py
fig/backends/__init__.py
fig/backends/aws/__init__.py
fig/backends/aws_sqs/__init__.py
fig/backends/azure/__init__.py
fig/backends/cloudtrail_lake/__init__.py
fig/backends/cloudtrail_lake/cloudtrail_offset.py
fig/backends/gcp/__init__.py
fig/backends/gcp/api/__init__.py
fig/backends/gcp/api/scc.py
fig/backends/generic/__init__.py
fig/backends/workspaceone/__init__.py
fig/backends/workspaceone/serverlog/__init__.py
fig/config/__init__.py
fig/config/credstore.py
fig/falcon/__init__.py
fig/falcon/api.py
fig/falcon/errors.py
fig/falcon/models.py
fig/falcon/rtr.py
fig/falcon/stream.py
fig/log/__init__.py
fig/queue/__init__.py
fig/util/__init__.py
fig/util/threading.py
falcon_integration_gateway-3.4.0.dist-info/METADATA
falcon_integration_gateway-3.4.0.dist-info/WHEEL
falcon_integration_gateway-3.4.0.dist-info/top_level.txt
falcon_integration_gateway-3.4.0.dist-info/RECORD
