Metadata-Version: 2.4
Name: falcon-integration-gateway
Version: 3.4.0
Summary: The CrowdStrike Demo Falcon Integration Gateway for GCP
Home-page: https://github.com/crowdstrike/falcon-integration-gateway
Author: CRWD Solution Architects
Author-email: integrations@crowdstrike.com
Classifier: Development Status :: 4 - Beta
Classifier: Intended Audience :: Developers
Classifier: Operating System :: Unix
Classifier: Operating System :: POSIX
Classifier: Operating System :: Microsoft :: Windows
Classifier: Programming Language :: Python :: 3
Classifier: License :: OSI Approved :: The Unlicense (Unlicense)
Classifier: Operating System :: OS Independent
Requires-Python: >=3.6, <3.12
License-File: LICENSE
Requires-Dist: boto3
Requires-Dist: crowdstrike-falconpy
Requires-Dist: google-cloud-securitycenter
Requires-Dist: google-cloud-resource-manager>=1.0.2
Requires-Dist: tls-syslog
Requires-Dist: google-auth
Requires-Dist: google-api-python-client
Requires-Dist: py7zr
Provides-Extra: devel
Requires-Dist: flake8; extra == "devel"
Requires-Dist: pylint; extra == "devel"
Requires-Dist: pytest; extra == "devel"
Requires-Dist: bandit; extra == "devel"
Dynamic: author
Dynamic: author-email
Dynamic: classifier
Dynamic: description
Dynamic: description-content-type
Dynamic: home-page
Dynamic: license-file
Dynamic: provides-extra
Dynamic: requires-dist
Dynamic: requires-python
Dynamic: summary
